<?xml version="1.0" encoding="utf-8"?>
<DesignMaterialDef ID="Stone: Granite" Enum="Stone_Granite">
  <CorrosionResistance>9</CorrosionResistance>
  <Density_kg_per_m3>2700</Density_kg_per_m3>
  <StackingHeight_m>2</StackingHeight_m>
  <ElasticModulus_GPa>70</ElasticModulus_GPa>
  <IsPropellant>false</IsPropellant>
  <IsSolid>true</IsSolid>
  <IsTreadCompound>false</IsTreadCompound>
  <IsCarcassRubber>false</IsCarcassRubber>
  <IsTireCord>false</IsTireCord>
  <IsRimMaterial>false</IsRimMaterial>
  <TensileStrength_MPa>18</TensileStrength_MPa>
  <ThermalExpansion_ppm_C>7</ThermalExpansion_ppm_C>
  <YieldStrength_MPa>130</YieldStrength_MPa>
  <Metallic>0.05</Metallic>
  <Roughness>0.7</Roughness>
  <Opacity>1</Opacity>
  <DesignMaterialDefEnum>Stone_Granite</DesignMaterialDefEnum>
  <EraDef>First</EraDef>
  <StorageCategoryDef>Yard Storage</StorageCategoryDef>
  <Name>Stone: Granite</Name>
  <ShortName>SG</ShortName>
</DesignMaterialDef>